medcv/__init__.py
medcv/version.py
medcv/data/__init__.py
medcv/data/chest.dcm
medcv/data/heatmap.jpg
medcv/data/lung_bbox.json
medcv/data/lung_mask.nii.gz
medcv/gui/QMedLabel.py
medcv/gui/QMedManger.py
medcv/gui/__init__.py
medcv/tools/__init__.py
medcv/tools/transform/__init__.py
medcv/tools/transform/med2grey.py
medcv/tools/transform/med2med.py
medcv/tools/transform/med2rgb.py
medcv/utils/__init__.py
medcv/utils/arg_support.py
medcv/utils/colors.py
medcv/utils/lut.py
medcv/utils/lut_fn.py
medcv/visualize/__init__.py
medcv/visualize/cls.py
medcv/visualize/det.py
medcv/visualize/seg.py
medcv-1.0.0.dist-info/DESCRIPTION.rst
medcv-1.0.0.dist-info/METADATA
medcv-1.0.0.dist-info/RECORD
medcv-1.0.0.dist-info/WHEEL
medcv-1.0.0.dist-info/metadata.json
medcv-1.0.0.dist-info/top_level.txt
